text_animator/__init__.py
text_animator/animator.py
text_animator-0.1.0.dist-info/METADATA
text_animator-0.1.0.dist-info/WHEEL
text_animator-0.1.0.dist-info/namespace_packages.txt
text_animator-0.1.0.dist-info/top_level.txt
text_animator-0.1.0.dist-info/zip-safe
text_animator-0.1.0.dist-info/RECORD
