Metadata-Version: 2.1
Name: text-animator
Version: 0.1.0
Summary: A simple text animator
Home-page: https://github.com/soda480/text-animator
Author: Emilio Reyes
Author-email: soda480@gmail.com
Maintainer: 
Maintainer-email: 
License: Apache License, Version 2.0
Classifier: Programming Language :: Python
Classifier: Programming Language :: Python :: 3.7
Classifier: Programming Language :: Python :: 3.8
Classifier: Programming Language :: Python :: 3.9
Classifier: Programming Language :: Python :: 3.10
Requires-Dist: ascii-animator
